{
  "Physical_Process": [
    {
      "group": "principal",
      "items": [
        {
          "slot": "implements_business_process",
          "label": "Business Process",
          "widget_type": "InstanceFieldWidget",
          "order": 1
        },
        {
          "slot": "process_performed_by_actor_role",
          "label": "Performed By Organisation",
          "widget_type": "InstanceFieldWidget",
          "order": 2
        },
        {
          "slot": "description",
          "label": "Description",
          "widget_type": "TextAreaWidget",
          "order": 3
        },
        {
          "slot": "physbusproc_uses_appinforeps",
          "label": "Supporting Information",
          "widget_type": "InstanceListWidget",
          "order": 4
        },
        {
          "slot": "phys_bp_supported_by_app_pro",
          "label": "Supporting Applications",
          "widget_type": "InstanceListWidget",
          "order": 5
        },
        {
          "slot": "name",
          "label": "Full Name",
          "widget_type": "AutoTextWidget",
          "order": 6
        },
        {
          "slot": "stakeholders",
          "label": "Stakeholders",
          "widget_type": "InstanceListWidget",
          "order": 7
        },
        {
          "slot": "phys_bp_supported_by_app_funimpl",
          "label": "Supporting Application Functions",
          "widget_type": "InstanceListWidget",
          "order": 8
        },
        {
          "slot": "physical_process_automated_by",
          "label": "Physical Process Automated By",
          "widget_type": "InstanceListWidget",
          "order": 9
        },
        {
          "slot": "process_performed_at_sites",
          "label": "Process Performed At Sites",
          "widget_type": "InstanceListWidget",
          "order": 10
        },
        {
          "slot": "parent_physical_processes",
          "label": "Parent Physical Processes",
          "widget_type": "InstanceListWidget",
          "order": 11
        },
        {
          "slot": "inverse_of_contained_physical_sub_processes",
          "label": "Contained in Physical Processes",
          "widget_type": "InstanceListWidget",
          "order": 12
        },
        {
          "slot": "contained_physical_sub_processes",
          "label": "Contained Physical Sub Processes",
          "widget_type": "InstanceListWidget",
          "order": 13
        },
        {
          "slot": "known_business_issues",
          "label": "Known Business Issues",
          "widget_type": "InstanceListWidget",
          "order": 14
        }
      ]
    },
    {
      "group": "extra",
      "items": [
        {
          "slot": "supersedes_version",
          "label": "Superseded Version",
          "widget_type": "InstanceFieldWidget",
          "order": 15
        },
        {
          "slot": "element_classified_by",
          "label": "Classified As",
          "widget_type": "InstanceListWidget",
          "order": 16
        },
        {
          "slot": "external_reference_links",
          "label": "External Reference Links",
          "widget_type": "InstanceListWidget",
          "order": 17
        },
        {
          "slot": "external_repository_instance_reference",
          "label": "External Repository Instance Reference",
          "widget_type": "InstanceListWidget",
          "order": 18
        },
        {
          "slot": "bus_physical_contained_in_arch_states",
          "label": "Contained In Architecture States",
          "widget_type": "InstanceListWidget",
          "order": 19
        },
        {
          "slot": "synonyms",
          "label": "Synonyms",
          "widget_type": "InstanceListWidget",
          "order": 20
        },
        {
          "slot": "process_manager",
          "label": "Process Manager",
          "widget_type": "InstanceFieldWidget",
          "order": 21
        },
        {
          "slot": "lifecycle_model_for_element",
          "label": "Lifecycle Model For Element",
          "widget_type": "InstanceListWidget",
          "order": 22
        },
        {
          "slot": "performance_measures",
          "label": "Performance Measures",
          "widget_type": "InstanceListWidget",
          "order": 23
        },
        {
          "slot": "coord_x",
          "label": "Coord X",
          "widget_type": "IntegerFieldWidget",
          "order": 24
        },
        {
          "slot": "coord_y",
          "label": "Coord Y",
          "widget_type": "IntegerFieldWidget",
          "order": 25
        },
        {
          "slot": "element_styling_classes",
          "label": "Element Styling Classes",
          "widget_type": "InstanceListWidget",
          "order": 26
        },
        {
          "slot": "scale_x",
          "label": "Scale X",
          "widget_type": "FloatFieldWidget",
          "order": 28
        },
        {
          "slot": "scale_y",
          "label": "Scale Y",
          "widget_type": "FloatFieldWidget",
          "order": 29
        },
        {
          "slot": "commentary",
          "label": "Commentary",
          "widget_type": "InstanceListWidget",
          "order": 30
        }
      ]
    },
    {
      "group": "security",
      "items": [
        {
          "slot": "system_security_read_classification",
          "label": "System Security Read Classification",
          "widget_type": "InstanceListWidget",
          "order": 27
        },
        {
          "slot": "system_security_edit_classification",
          "label": "System Security Edit Classification",
          "widget_type": "InstanceListWidget",
          "order": 31
        }
      ]
    }
  ]
}